pollination/daylight_factor/__init__.py
pollination/daylight_factor/_postprocess_results.py
pollination/daylight_factor/_prepare_folder.py
pollination/daylight_factor/entry.py
pollination_daylight_factor-0.8.15.dist-info/LICENSE
pollination_daylight_factor-0.8.15.dist-info/METADATA
pollination_daylight_factor-0.8.15.dist-info/WHEEL
pollination_daylight_factor-0.8.15.dist-info/top_level.txt
pollination_daylight_factor-0.8.15.dist-info/RECORD
